iitjp/__init__.py
iitjp/__main__.py
iitjp/rajlaxmi.py
iitjp/data/end_quiz.wav
iitjp/data/farewell.wav
iitjp/data/greeting.wav
iitjp/data/questions.json
iitjp/data/start_quiz.wav
iitjp-0.2.18.data/data/data/end_quiz.wav
iitjp-0.2.18.data/data/data/farewell.wav
iitjp-0.2.18.data/data/data/greeting.wav
iitjp-0.2.18.data/data/data/questions.json
iitjp-0.2.18.data/data/data/start_quiz.wav
iitjp-0.2.18.dist-info/licenses/LICENSE
iitjp-0.2.18.dist-info/METADATA
iitjp-0.2.18.dist-info/WHEEL
iitjp-0.2.18.dist-info/entry_points.txt
iitjp-0.2.18.dist-info/top_level.txt
iitjp-0.2.18.dist-info/RECORD
