Metadata-Version: 2.4
Name: iitjp
Version: 0.2.18
Summary: A virtual teaching assistant with voice capabilities for Statistics education.
Home-page: https://github.com/yutkarsh.brainstorm/ourusername/IITJP
Author: Utkarsh Yadav
Author-email: Utkarsh Yadav <utkarsh.brainstorm@gmail.com>
License-Expression: MIT
Project-URL: Homepage, https://github.com/utkarsh-brainstorm/IITJP
Project-URL: Bug Tracker, https://github.com/utkarsh-brainstorm/IITJP/issues
Classifier: Development Status :: 4 - Beta
Classifier: Intended Audience :: Education
Classifier: Programming Language :: Python :: 3
Classifier: Programming Language :: Python :: 3.7
Classifier: Programming Language :: Python :: 3.8
Classifier: Programming Language :: Python :: 3.9
Classifier: Programming Language :: Python :: 3.10
Classifier: Programming Language :: Python :: 3.11
Classifier: Operating System :: OS Independent
Classifier: Topic :: Education
Classifier: Topic :: Software Development :: Libraries
Requires-Python: >=3.7
License-File: LICENSE
Requires-Dist: numpy>=1.21.0
Requires-Dist: scipy>=1.7.0
Requires-Dist: pyaudio>=0.2.11
Requires-Dist: setuptools>=44.0.0
Dynamic: author
Dynamic: home-page
Dynamic: license-file
Dynamic: requires-python
